{
  "project_info": {
    "project_number": "997519386620",
    "project_id": "cars2-2ed38",
    "storage_bucket": "cars2-2ed38.appspot.com"
  },
  "client": [
    {
      "client_info": {
        "mobilesdk_app_id": "1:997519386620:android:c287b410b1678fab543479",
        "android_client_info": {
          "package_name": "com.example.cars"
        }
      },
      "oauth_client": [],
      "api_key": [
        {
          "current_key": "AIzaSyDbpfMAXSiYxuHvAPsAhyo4Rwc1R0e51oY"
        }
      ],
      "services": {
        "appinvite_service": {
          "other_platform_oauth_client": []
        }
      }
    }
  ],
  "configuration_version": "1"
}